miko/__init__.py
miko/builtins.py
miko/manager.py
miko/parser.py
miko/py.typed
miko/template.py
miko/utils.py
miko_tpl-1.3.3.dist-info/LICENSE
miko_tpl-1.3.3.dist-info/METADATA
miko_tpl-1.3.3.dist-info/WHEEL
miko_tpl-1.3.3.dist-info/top_level.txt
miko_tpl-1.3.3.dist-info/RECORD
