Metadata-Version: 2.1
Name: miko-tpl
Version: 1.3.3
Summary: Little, lightweight and fast template engine.
Home-page: https://github.com/tasuren/miko
Author: tasuren
Author-email: tasuren@aol.com
License: MIT
Project-URL: Documentation, https://miko.readthedocs.io/
Keywords: template engine
Platform: UNKNOWN
Classifier: Programming Language :: Python :: 3.10
Classifier: Topic :: Text Processing :: Markup :: HTML
Classifier: Typing :: Typed
Requires-Python: >=3.10.0
